{
  "schemaVersion": 1,
  "id": "ch1-b4",
  "terrain": [
    [
      [
        -7.5,
        2.6
      ],
      [
        -2.4,
        2.6
      ],
      [
        -2.2,
        -5
      ]
    ],
    [
      [
        1.5,
        -5
      ],
      [
        1.7,
        0.6
      ],
      [
        3.1,
        0.6
      ],
      [
        3.3,
        -5
      ]
    ],
    [
      [
        7,
        -5
      ],
      [
        7.2,
        -1.4
      ],
      [
        10,
        -1.4
      ]
    ]
  ],
  "vehicleSpawn": {
    "x": -4,
    "y": 2.95
  },
  "goalFlag": {
    "x": 7.8,
    "y": -1.4,
    "width": 1,
    "height": 2
  },
  "killY": -11,
  "inkBudget": 34.92,
  "starThresholds": {
    "star3": 12.8,
    "star2": 15.72
  },
  "coins": [
    {
      "x": -3.223,
      "y": 3.396
    },
    {
      "x": -1.423,
      "y": 3.194
    },
    {
      "x": 0.138,
      "y": 2.284
    },
    {
      "x": 1.795,
      "y": 1.603
    },
    {
      "x": 3.597,
      "y": 1.741
    },
    {
      "x": 5.348,
      "y": 1.303
    },
    {
      "x": 6.876,
      "y": 0.328
    }
  ],
  "gimmickTags": [],
  "ghostSolutions": [
    {
      "kind": "any",
      "stroke": [
        [
          -3,
          2.62
        ],
        [
          -0.4,
          1.6
        ],
        [
          1.4411078717201167,
          0.7082215743440238
        ],
        [
          1.9306122448979592,
          0.5774927113702625
        ],
        [
          2.1306122448979594,
          0.5783090379008746
        ],
        [
          2.669387755102041,
          0.6657725947521864
        ],
        [
          2.869387755102041,
          0.6649562682215742
        ],
        [
          3.1,
          0.62
        ],
        [
          3.634402332361516,
          0.40174927113702624
        ],
        [
          5.2,
          -0.4
        ],
        [
          7.8,
          -1.38
        ]
      ],
      "sampleEveryTicks": 10,
      "samples": [
        {
          "t": 0,
          "x": -3.9998394550879635,
          "y": 3.100453261373676
        },
        {
          "t": 10,
          "x": -3.9998394550879635,
          "y": 3.100453261373676
        },
        {
          "t": 20,
          "x": -3.9998394550879635,
          "y": 3.100453261373676
        },
        {
          "t": 30,
          "x": -3.949922095862282,
          "y": 3.096748690649331
        },
        {
          "t": 40,
          "x": -3.720403475805563,
          "y": 3.0976701893780265
        },
        {
          "t": 50,
          "x": -3.34581746444269,
          "y": 3.0968173867910345
        },
        {
          "t": 60,
          "x": -2.8133252617862667,
          "y": 3.0934922427308567
        },
        {
          "t": 70,
          "x": -2.1010732754783144,
          "y": 3.0294397173576133
        },
        {
          "t": 80,
          "x": -1.2477953917776659,
          "y": 2.8357156665568386
        },
        {
          "t": 90,
          "x": -0.38761991566143816,
          "y": 2.3650005960776697
        },
        {
          "t": 100,
          "x": 0.45623509046081434,
          "y": 1.7766686224696464
        },
        {
          "t": 110,
          "x": 1.3458128445083937,
          "y": 1.3688632856078522
        },
        {
          "t": 120,
          "x": 2.344727714637414,
          "y": 1.400386013372248
        },
        {
          "t": 130,
          "x": 3.387032753584532,
          "y": 1.4514132320834863
        },
        {
          "t": 140,
          "x": 4.482264575987022,
          "y": 1.3134494079532864
        },
        {
          "t": 150,
          "x": 5.576729524267278,
          "y": 0.8917083274402494
        },
        {
          "t": 160,
          "x": 6.670934129524618,
          "y": 0.19074808307812666
        },
        {
          "t": 170,
          "x": 7.756712196232149,
          "y": -0.7423071258200398
        },
        {
          "t": 171,
          "x": 7.862382337395121,
          "y": -0.8145291867627963
        }
      ],
      "result": {
        "outcome": "clear",
        "ticks": 171,
        "finalPos": {
          "x": 7.862382337395121,
          "y": -0.8145291867627963
        },
        "inkConsumed": 11.640839644236145,
        "starRating": 3
      }
    }
  ],
  "bonusMultiplier": 5
}
