{
  "schemaVersion": 1,
  "id": "ch1-l10",
  "terrain": [
    [
      [
        -13,
        0
      ],
      [
        -2.7,
        0
      ],
      [
        -2.9000000000000004,
        -6
      ]
    ],
    [
      [
        2.9000000000000004,
        -6
      ],
      [
        2.7,
        2.2
      ],
      [
        16,
        2.2
      ]
    ]
  ],
  "vehicleSpawn": {
    "x": -8,
    "y": 0.6
  },
  "goalFlag": {
    "x": 12,
    "y": 2.2,
    "width": 1.2,
    "height": 2.2
  },
  "killY": -8,
  "inkBudget": 8.88,
  "starThresholds": {
    "star2": 8.44,
    "star3": 6.66
  },
  "coins": [
    {
      "x": -1.85,
      "y": 1.7
    },
    {
      "x": -1.3,
      "y": 1.95
    },
    {
      "x": -0.75,
      "y": 2.1
    },
    {
      "x": -0.19999999999999996,
      "y": 2.15
    },
    {
      "x": 0.3500000000000001,
      "y": 2.1
    },
    {
      "x": 0.8999999999999999,
      "y": 1.95
    },
    {
      "x": 1.4500000000000002,
      "y": 1.7
    }
  ],
  "gimmickTags": [
    "anti-dominant"
  ],
  "ghostSolutions": [
    {
      "kind": "any",
      "stroke": [
        [
          -4.2,
          0.3
        ],
        [
          -2.225,
          1.15
        ],
        [
          -0.25,
          1.7750000000000001
        ],
        [
          1.7250000000000005,
          2.1750000000000003
        ],
        [
          3.7,
          2.35
        ]
      ],
      "sampleEveryTicks": 10,
      "samples": [
        {
          "t": 0,
          "x": -7.999999298446202,
          "y": 0.5007129518888385
        },
        {
          "t": 10,
          "x": -7.999999298446202,
          "y": 0.5007129518888385
        },
        {
          "t": 20,
          "x": -7.999999298446202,
          "y": 0.5007129518888385
        },
        {
          "t": 30,
          "x": -7.953723540960365,
          "y": 0.49865804680048387
        },
        {
          "t": 40,
          "x": -7.721410477620085,
          "y": 0.4999784950143407
        },
        {
          "t": 50,
          "x": -7.325360208100825,
          "y": 0.49880553486721024
        },
        {
          "t": 60,
          "x": -6.77227284472707,
          "y": 0.4978244883256158
        },
        {
          "t": 70,
          "x": -6.072074148143622,
          "y": 0.49714312000477495
        },
        {
          "t": 80,
          "x": -5.3113724561454125,
          "y": 0.4951029645946343
        },
        {
          "t": 90,
          "x": -4.769080622577579,
          "y": 0.5922230556705944
        },
        {
          "t": 100,
          "x": -4.236360034571672,
          "y": 0.7190369994729732
        },
        {
          "t": 110,
          "x": -3.6934467624135925,
          "y": 0.8380046057723367
        },
        {
          "t": 120,
          "x": -3.1842631758664566,
          "y": 0.85566127612669
        },
        {
          "t": 130,
          "x": -2.66329014140416,
          "y": 0.6863255577776838
        },
        {
          "t": 140,
          "x": -2.012108731809037,
          "y": 0.6701464395382174
        },
        {
          "t": 150,
          "x": -1.242258762585844,
          "y": 0.6724929266755637
        },
        {
          "t": 160,
          "x": -0.562941117776573,
          "y": 0.6182147418323851
        },
        {
          "t": 170,
          "x": 0.034131909684046224,
          "y": 0.7440901297313706
        },
        {
          "t": 180,
          "x": 0.5832525809970952,
          "y": 1.1459384129892969
        },
        {
          "t": 190,
          "x": 1.0989468935899844,
          "y": 1.4964902048189508
        },
        {
          "t": 200,
          "x": 1.566883115317851,
          "y": 1.8864660365113213
        },
        {
          "t": 210,
          "x": 1.8989097559027548,
          "y": 2.434207554691371
        },
        {
          "t": 220,
          "x": 2.1913562527345403,
          "y": 2.8973032362264104
        },
        {
          "t": 230,
          "x": 2.4343808647463008,
          "y": 3.2582752987714123
        },
        {
          "t": 240,
          "x": 2.6340494096103373,
          "y": 3.4683009340928406
        },
        {
          "t": 250,
          "x": 2.830583754231531,
          "y": 3.4727297570417504
        },
        {
          "t": 260,
          "x": 3.0404486038991823,
          "y": 3.4376107325519514
        },
        {
          "t": 270,
          "x": 3.289878015317657,
          "y": 3.460785049447864
        },
        {
          "t": 280,
          "x": 3.5957300232558858,
          "y": 3.4117853133640246
        },
        {
          "t": 290,
          "x": 4.0088196368945335,
          "y": 3.257182765282964
        },
        {
          "t": 300,
          "x": 4.458337165754713,
          "y": 2.8470290544254464
        },
        {
          "t": 310,
          "x": 5.061920406225381,
          "y": 2.5935084605233674
        },
        {
          "t": 320,
          "x": 5.8222315445019,
          "y": 2.719195921011664
        },
        {
          "t": 330,
          "x": 6.580197491890798,
          "y": 2.7003986313737984
        },
        {
          "t": 340,
          "x": 7.32037283986732,
          "y": 2.6904884301747805
        },
        {
          "t": 350,
          "x": 8.0604076130862,
          "y": 2.6964205474622154
        },
        {
          "t": 360,
          "x": 8.80441096204031,
          "y": 2.695520702657774
        },
        {
          "t": 370,
          "x": 9.548739736358966,
          "y": 2.695077162769119
        },
        {
          "t": 380,
          "x": 10.292300488885587,
          "y": 2.695351497453179
        },
        {
          "t": 390,
          "x": 11.03577012722338,
          "y": 2.6953110037243135
        },
        {
          "t": 400,
          "x": 11.77940713791856,
          "y": 2.695289767358286
        },
        {
          "t": 403,
          "x": 12.002509664778817,
          "y": 2.6952943487272796
        }
      ],
      "result": {
        "outcome": "clear",
        "ticks": 403,
        "finalPos": {
          "x": 12.002509664778817,
          "y": 2.6952943487272796
        },
        "inkConsumed": 8.21951585153961,
        "starRating": 2
      }
    }
  ],
  "maxTicks": 1800
}
