{
  "schemaVersion": 1,
  "id": "ch1-l14",
  "terrain": [
    [
      [
        -9,
        0.4
      ],
      [
        -2.7,
        0.4
      ],
      [
        -2.9,
        -5.8
      ],
      [
        2.9,
        -5.8
      ],
      [
        2.7,
        0.4
      ],
      [
        3.6,
        0.4
      ],
      [
        4.2,
        0.9
      ],
      [
        9,
        0.9
      ]
    ],
    [
      [
        -0.8,
        -5.8
      ],
      [
        -0.45,
        1.55
      ],
      [
        0.45,
        1.55
      ],
      [
        0.8,
        -5.8
      ]
    ]
  ],
  "vehicleSpawn": {
    "x": -6.6,
    "y": 0.75
  },
  "goalFlag": {
    "x": 6.4,
    "y": 0.9,
    "width": 1,
    "height": 2
  },
  "killY": -11.8,
  "inkBudget": 17.5,
  "starThresholds": {
    "star3": 7.7,
    "star2": 9.45
  },
  "coins": [
    {
      "x": -5.758,
      "y": 1.196
    },
    {
      "x": -3.414,
      "y": 1.361
    },
    {
      "x": -1.296,
      "y": 2.331
    },
    {
      "x": 0.811,
      "y": 3.167
    },
    {
      "x": 2.797,
      "y": 1.921
    },
    {
      "x": 5.042,
      "y": 1.78
    }
  ],
  "gimmickTags": [],
  "ghostSolutions": [
    {
      "kind": "any",
      "stroke": [
        [
          -3.2,
          0.4
        ],
        [
          -2.7,
          0.42
        ],
        [
          -1.385422740524782,
          1.24731778425656
        ],
        [
          -0.9504373177842566,
          1.4661807580174928
        ],
        [
          -0.698542274052478,
          1.5287172011661811
        ],
        [
          -0.07667638483965016,
          1.5744897959183675
        ],
        [
          0.5,
          1.55
        ],
        [
          0.9504373177842567,
          1.4661807580174926
        ],
        [
          1.3854227405247814,
          1.24731778425656
        ],
        [
          2.7,
          0.42
        ],
        [
          3.2,
          0.4
        ]
      ],
      "sampleEveryTicks": 10,
      "samples": [
        {
          "t": 0,
          "x": -6.599839455087975,
          "y": 0.9004532613736758
        },
        {
          "t": 10,
          "x": -6.599839455087975,
          "y": 0.9004532613736758
        },
        {
          "t": 20,
          "x": -6.599839455087975,
          "y": 0.9004532613736758
        },
        {
          "t": 30,
          "x": -6.549922095862294,
          "y": 0.8967486906493307
        },
        {
          "t": 40,
          "x": -6.301442587528513,
          "y": 0.8975437774440818
        },
        {
          "t": 50,
          "x": -5.892709964437419,
          "y": 0.8968664152807149
        },
        {
          "t": 60,
          "x": -5.3281784820858045,
          "y": 0.8957416553443585
        },
        {
          "t": 70,
          "x": -4.598707707039988,
          "y": 0.8958551593342963
        },
        {
          "t": 80,
          "x": -3.8400058664420715,
          "y": 0.9504386886814422
        },
        {
          "t": 90,
          "x": -3.132706986213709,
          "y": 1.1064493082437337
        },
        {
          "t": 100,
          "x": -2.3841476802096198,
          "y": 1.3710842057380015
        },
        {
          "t": 110,
          "x": -1.7215427203990628,
          "y": 1.719595192529754
        },
        {
          "t": 120,
          "x": -1.054228231356511,
          "y": 2.225444582930251
        },
        {
          "t": 130,
          "x": -0.37785333100558166,
          "y": 2.7022901705400444
        },
        {
          "t": 140,
          "x": 0.3032749229123508,
          "y": 2.9012788857978697
        },
        {
          "t": 150,
          "x": 0.9852341069245657,
          "y": 2.8207980238790533
        },
        {
          "t": 160,
          "x": 1.6674191897263086,
          "y": 2.4621359920266146
        },
        {
          "t": 170,
          "x": 2.424422663090812,
          "y": 1.8655086290914533
        },
        {
          "t": 180,
          "x": 3.484787452549427,
          "y": 1.2903228707149121
        },
        {
          "t": 190,
          "x": 4.6099344075785895,
          "y": 1.3539094654688224
        },
        {
          "t": 200,
          "x": 5.5819408886001565,
          "y": 1.5788653904032837
        },
        {
          "t": 209,
          "x": 6.438330297175885,
          "y": 1.6324180553859864
        }
      ],
      "result": {
        "outcome": "clear",
        "ticks": 209,
        "finalPos": {
          "x": 6.438330297175885,
          "y": 1.6324180553859864
        },
        "inkConsumed": 6.999629825743678,
        "starRating": 3
      }
    }
  ],
  "dangerZones": [
    {
      "x": -2.6,
      "y": -5.2,
      "width": 5.2,
      "height": 0.9,
      "style": "spike"
    }
  ],
  "solutions": [
    {
      "shapeTag": "trapezoid",
      "stroke": [
        [
          -3.2,
          0.4
        ],
        [
          -2.7,
          0.42
        ],
        [
          -2.557434402332362,
          0.5104373177842566
        ],
        [
          -2.3574344023323617,
          0.6392128279883382
        ],
        [
          -2.120116618075802,
          0.7918075801749271
        ],
        [
          -1.8655976676384842,
          0.9537026239067055
        ],
        [
          -1.6139941690962107,
          1.1103790087463559
        ],
        [
          -1.385422740524782,
          1.24731778425656
        ],
        [
          -1.2,
          1.35
        ],
        [
          -1.0606413994169093,
          1.4186297376093295
        ],
        [
          -0.9504373177842566,
          1.4661807580174928
        ],
        [
          -0.8597667638483965,
          1.4972886297376096
        ],
        [
          -0.7790087463556852,
          1.516588921282799
        ],
        [
          -0.698542274052478,
          1.5287172011661811
        ],
        [
          -0.6087463556851311,
          1.538309037900875
        ],
        [
          -0.5,
          1.55
        ],
        [
          -0.37026239067055394,
          1.5622448979591836
        ],
        [
          -0.22740524781341112,
          1.570408163265306
        ],
        [
          -0.07667638483965016,
          1.5744897959183675
        ],
        [
          0.0766763848396501,
          1.5744897959183675
        ],
        [
          0.22740524781341104,
          1.5704081632653062
        ],
        [
          0.370262390670554,
          1.5622448979591836
        ],
        [
          0.5,
          1.55
        ],
        [
          0.6087463556851312,
          1.5383090379008748
        ],
        [
          0.6985422740524782,
          1.528717201166181
        ],
        [
          0.7790087463556852,
          1.5165889212827988
        ],
        [
          0.8597667638483963,
          1.4972886297376093
        ],
        [
          0.9504373177842567,
          1.4661807580174926
        ],
        [
          1.0606413994169097,
          1.4186297376093293
        ],
        [
          1.2,
          1.35
        ],
        [
          1.3854227405247814,
          1.24731778425656
        ],
        [
          1.6139941690962099,
          1.1103790087463556
        ],
        [
          1.8655976676384838,
          0.9537026239067056
        ],
        [
          2.1201166180758015,
          0.7918075801749271
        ],
        [
          2.3574344023323612,
          0.6392128279883382
        ],
        [
          2.5574344023323614,
          0.5104373177842568
        ],
        [
          2.7,
          0.42
        ],
        [
          3.2,
          0.4
        ]
      ]
    },
    {
      "shapeTag": "angle",
      "stroke": [
        [
          -3.2,
          0.4
        ],
        [
          -2.7,
          0.42
        ],
        [
          0,
          1.7
        ],
        [
          2.7,
          0.42
        ],
        [
          3.2,
          0.4
        ]
      ]
    }
  ]
}
