{
  "schemaVersion": 1,
  "id": "ch1-l15",
  "terrain": [
    [
      [
        -13,
        0
      ],
      [
        -2.7,
        0
      ],
      [
        -2.9000000000000004,
        -6.5
      ]
    ],
    [
      [
        2.9000000000000004,
        -6.5
      ],
      [
        2.7,
        2.2
      ],
      [
        18,
        2.2
      ]
    ]
  ],
  "vehicleSpawn": {
    "x": -8,
    "y": 0.6
  },
  "goalFlag": {
    "x": 14,
    "y": 2.2,
    "width": 1.2,
    "height": 2.2
  },
  "killY": -8.5,
  "inkBudget": 7.14,
  "starThresholds": {
    "star2": 6.78,
    "star3": 5.36
  },
  "coins": [
    {
      "x": -1.85,
      "y": 1.7
    },
    {
      "x": -1.3,
      "y": 1.9777777777777776
    },
    {
      "x": -0.75,
      "y": 2.1444444444444444
    },
    {
      "x": -0.19999999999999996,
      "y": 2.2
    },
    {
      "x": 0.3500000000000001,
      "y": 2.1444444444444444
    },
    {
      "x": 0.8999999999999999,
      "y": 1.9777777777777776
    },
    {
      "x": 1.4500000000000002,
      "y": 1.7
    }
  ],
  "gimmickTags": [
    "anti-dominant"
  ],
  "ghostSolutions": [
    {
      "kind": "any",
      "stroke": [
        [
          -3.2,
          0.15
        ],
        [
          -1.6500000000000001,
          0.925
        ],
        [
          -0.10000000000000009,
          1.55
        ],
        [
          1.4500000000000002,
          2.025
        ],
        [
          3,
          2.35
        ]
      ],
      "sampleEveryTicks": 10,
      "samples": [
        {
          "t": 0,
          "x": -7.999999298446202,
          "y": 0.5007129518888385
        },
        {
          "t": 10,
          "x": -7.999999298446202,
          "y": 0.5007129518888385
        },
        {
          "t": 20,
          "x": -7.999999298446202,
          "y": 0.5007129518888385
        },
        {
          "t": 30,
          "x": -7.950148401816137,
          "y": 0.496791845426991
        },
        {
          "t": 40,
          "x": -7.701716778764075,
          "y": 0.4975000345275083
        },
        {
          "t": 50,
          "x": -7.292932337373262,
          "y": 0.496877440606143
        },
        {
          "t": 60,
          "x": -6.728386001113686,
          "y": 0.49574314545232023
        },
        {
          "t": 70,
          "x": -5.9989104510641855,
          "y": 0.49585266580783527
        },
        {
          "t": 80,
          "x": -5.107291468154174,
          "y": 0.49559491718909954
        },
        {
          "t": 90,
          "x": -4.144505957653408,
          "y": 0.5222685685143464
        },
        {
          "t": 100,
          "x": -3.3834369308456766,
          "y": 0.7190187907692982
        },
        {
          "t": 110,
          "x": -2.5798234210420183,
          "y": 0.9830441088168335
        },
        {
          "t": 120,
          "x": -1.820243362037317,
          "y": 1.1978718259166503
        },
        {
          "t": 130,
          "x": -1.074680395733459,
          "y": 1.4295231380978164
        },
        {
          "t": 140,
          "x": -0.27582045329353994,
          "y": 1.774448034298751
        },
        {
          "t": 150,
          "x": 0.6048797094111972,
          "y": 2.128951736806489
        },
        {
          "t": 160,
          "x": 1.475599184498528,
          "y": 2.463587545819515
        },
        {
          "t": 170,
          "x": 2.3477916296331918,
          "y": 2.8654493000434385
        },
        {
          "t": 180,
          "x": 3.281772317886864,
          "y": 3.205000327078666
        },
        {
          "t": 190,
          "x": 4.25279501172783,
          "y": 3.370539454147063
        },
        {
          "t": 200,
          "x": 5.226015713539668,
          "y": 3.2503450987522897
        },
        {
          "t": 210,
          "x": 6.199210827351405,
          "y": 2.8497683199916684
        },
        {
          "t": 220,
          "x": 7.172665997115548,
          "y": 2.5878220446096636
        },
        {
          "t": 230,
          "x": 8.29971278847393,
          "y": 2.7072595628156324
        },
        {
          "t": 240,
          "x": 9.50256853211805,
          "y": 2.703065941555255
        },
        {
          "t": 250,
          "x": 10.696953020740958,
          "y": 2.687545711627837
        },
        {
          "t": 260,
          "x": 11.878022026319684,
          "y": 2.6934015732414816
        },
        {
          "t": 270,
          "x": 13.060069650491009,
          "y": 2.6936074262213965
        },
        {
          "t": 278,
          "x": 14.007975687563647,
          "y": 2.692773509535789
        }
      ],
      "result": {
        "outcome": "clear",
        "ticks": 278,
        "finalPos": {
          "x": 14.007975687563647,
          "y": 2.692773509535789
        },
        "inkConsumed": 6.609072554056697,
        "starRating": 2
      }
    }
  ],
  "maxTicks": 1800
}
