{
  "schemaVersion": 2,
  "id": "ch1-l09",
  "terrain": [
    [
      [
        -9,
        0
      ],
      [
        -2.6,
        0
      ],
      [
        -2.8,
        -6
      ]
    ],
    [
      [
        -1.1,
        -6
      ],
      [
        -0.7,
        0
      ],
      [
        0.7,
        0
      ],
      [
        1.1,
        -6
      ]
    ],
    [
      [
        2.8,
        -6
      ],
      [
        2.6,
        0
      ],
      [
        9,
        0
      ]
    ]
  ],
  "vehicleSpawn": {
    "x": -6,
    "y": 0.35
  },
  "goalFlag": {
    "x": 6,
    "y": 0,
    "width": 1,
    "height": 2
  },
  "killY": -12,
  "inkBudget": 14.53,
  "starThresholds": {
    "star3": 7.85,
    "star2": 14.53
  },
  "coins": [
    {
      "x": -5.269,
      "y": 0.797
    },
    {
      "x": -2.723,
      "y": 1.002
    },
    {
      "x": -0.228,
      "y": 0.985
    },
    {
      "x": 2.325,
      "y": 0.995
    },
    {
      "x": 4.883,
      "y": 0.904
    }
  ],
  "gimmickTags": [],
  "ghostSolutions": [
    {
      "kind": "any",
      "stroke": [
        [
          -2.9,
          0.04
        ],
        [
          -1.4,
          -0.05
        ],
        [
          0,
          0.04
        ],
        [
          1.4,
          -0.05
        ],
        [
          2.9,
          0.04
        ]
      ],
      "sampleEveryTicks": 10,
      "samples": [
        {
          "t": 0,
          "x": -5.999839455087986,
          "y": 0.5004532613736757
        },
        {
          "t": 10,
          "x": -5.999839455087986,
          "y": 0.5004532613736757
        },
        {
          "t": 20,
          "x": -5.999839455087986,
          "y": 0.5004532613736757
        },
        {
          "t": 30,
          "x": -5.949922095862305,
          "y": 0.4967486906493306
        },
        {
          "t": 40,
          "x": -5.701442587528525,
          "y": 0.49754377744408146
        },
        {
          "t": 50,
          "x": -5.292775566180028,
          "y": 0.49681846451063083
        },
        {
          "t": 60,
          "x": -4.728654535904476,
          "y": 0.4952708462051048
        },
        {
          "t": 70,
          "x": -3.9997643952894295,
          "y": 0.49535824901789904
        },
        {
          "t": 80,
          "x": -3.357634315987819,
          "y": 0.5990195369359161
        },
        {
          "t": 90,
          "x": -2.638781546610221,
          "y": 0.7122243441625782
        },
        {
          "t": 100,
          "x": -1.9192940927424262,
          "y": 0.9270562727615458
        },
        {
          "t": 110,
          "x": -1.2195762250439812,
          "y": 0.9044255728127285
        },
        {
          "t": 120,
          "x": -0.549983293320265,
          "y": 0.7050462078862718
        },
        {
          "t": 130,
          "x": 0.27109999905249593,
          "y": 0.7467482816487057
        },
        {
          "t": 140,
          "x": 1.2782832992237112,
          "y": 0.8080184458946118
        },
        {
          "t": 150,
          "x": 2.3433811718582227,
          "y": 0.6935084023452375
        },
        {
          "t": 160,
          "x": 3.4794433519577472,
          "y": 0.7197471002166318
        },
        {
          "t": 170,
          "x": 4.697697709071496,
          "y": 0.6314632880168967
        },
        {
          "t": 180,
          "x": 5.871911948163463,
          "y": 0.4887067127933125
        },
        {
          "t": 182,
          "x": 6.098782403585943,
          "y": 0.46975344282148007
        }
      ],
      "result": {
        "outcome": "clear",
        "ticks": 182,
        "finalPos": {
          "x": 6.098782403585943,
          "y": 0.46975344282148007
        },
        "inkConsumed": 5.811174897746454,
        "starRating": 3
      }
    }
  ],
  "objective": {
    "type": "noBreak"
  }
}
